src/cli.py
bcat-0.0.2.dist-info/METADATA
bcat-0.0.2.dist-info/WHEEL
bcat-0.0.2.dist-info/entry_points.txt
bcat-0.0.2.dist-info/top_level.txt
bcat-0.0.2.dist-info/RECORD
