Metadata-Version: 2.1
Name: bcat
Version: 0.0.2
Requires-Dist: pyarrow
Requires-Dist: pandas
